sphinxcontrib_github_alt.py
sphinxcontrib_github_alt-1.2.dist-info/COPYING.md
sphinxcontrib_github_alt-1.2.dist-info/WHEEL
sphinxcontrib_github_alt-1.2.dist-info/METADATA
sphinxcontrib_github_alt-1.2.dist-info/RECORD
