Metadata-Version: 2.1
Name: sphinxcontrib_github_alt
Version: 1.2
Summary: Link to GitHub issues, pull requests, commits and users from Sphinx docs.
Home-page: https://github.com/jupyter/sphinxcontrib_github_alt
License: UNKNOWN
Author: Jupyter Development Team
Author-email: jupyter@googlegroups.com
Classifier: Framework :: Sphinx :: Extension
Classifier: License :: OSI Approved :: BSD License
Classifier: Topic :: Documentation :: Sphinx
Classifier: Topic :: Software Development :: Bug Tracking
Classifier: Topic :: Software Development :: Documentation
Classifier: Topic :: Software Development :: Version Control
Requires-Dist: docutils
Requires-Dist: sphinx
